bluelink/__init__.py
bluelink/bluelink.py
bluelink/cli.py
bluelink/errors.py
bluelink/utils.py
bluelink-1.0.0.dist-info/AUTHORS
bluelink-1.0.0.dist-info/METADATA
bluelink-1.0.0.dist-info/WHEEL
bluelink-1.0.0.dist-info/entry_points.txt
bluelink-1.0.0.dist-info/top_level.txt
bluelink-1.0.0.dist-info/RECORD
