Metadata-Version: 2.1
Name: bluelink
Version: 1.0.0
Summary: Unofficial API wrapper for Hyundais BlueLink.
Home-page: https://github.com/synchronizing/bluelink
Author: Felipe Faria
Author-email: felipefaria@me.com
License: MIT
Project-URL: Bug Tracker, https://github.com/synchronizing/bluelink/issues
Project-URL: Source Code, https://github.com/synchronizing/bluelink/tree/master
Keywords: bluelink
Platform: UNKNOWN
Classifier: Programming Language :: Python :: Implementation :: CPython
Classifier: Development Status :: 5 - Production/Stable
Classifier: License :: OSI Approved :: MIT License
Classifier: Natural Language :: English
Classifier: Topic :: Software Development :: Libraries
Classifier: Topic :: Utilities
Requires-Python: >=3.7
License-File: AUTHORS
Requires-Dist: click
Requires-Dist: requests
